swarmform/__init__.py
swarmform/sf_config.py
swarmform/core/__init__.py
swarmform/core/cluster.py
swarmform/core/swarm_dag.py
swarmform/core/swarmpad.py
swarmform/core/swarmwork.py
swarmform/core/clustering_algo/__init__.py
swarmform/core/clustering_algo/hrab_clustering.py
swarmform/core/clustering_algo/wpa_clustering.py
swarmform/examples/__init__.py
swarmform/examples/cluster_examples/__init__.py
swarmform/examples/cluster_examples/hrab_cluster.py
swarmform/examples/cluster_examples/wpa_cluster.py
swarmform/examples/paralleltask_examples/__init__.py
swarmform/examples/paralleltask_examples/ex_parallel_task.py
swarmform/examples/swarmpad_examples/__init__.py
swarmform/examples/swarmpad_examples/ex_swarmpad.py
swarmform/examples/workflow_generator_examples/__init__.py
swarmform/examples/workflow_generator_examples/generate_workflow_from_dax.py
swarmform/examples/workflow_generator_examples/generate_workflow_from_yaml_dict.py
swarmform/scripts/__init__.py
swarmform/scripts/sform_run.py
swarmform/user_objects/__init__.py
swarmform/user_objects/firetasks/__init__.py
swarmform/user_objects/firetasks/parallel_tasks.py
swarmform/util/__init__.py
swarmform/util/resource_wastage.py
swarmform/util/workflow_generator.py
SwarmForm-1.0.2.dist-info/LICENSE
SwarmForm-1.0.2.dist-info/METADATA
SwarmForm-1.0.2.dist-info/WHEEL
SwarmForm-1.0.2.dist-info/entry_points.txt
SwarmForm-1.0.2.dist-info/top_level.txt
SwarmForm-1.0.2.dist-info/RECORD
